odoo/addons/ssi_accountant_report_project/README.rst
odoo/addons/ssi_accountant_report_project/__init__.py
odoo/addons/ssi_accountant_report_project/__manifest__.py
odoo/addons/ssi_accountant_report_project/models/__init__.py
odoo/addons/ssi_accountant_report_project/models/accountant_assurance_report.py
odoo/addons/ssi_accountant_report_project/models/accountant_nonassurance_report.py
odoo/addons/ssi_accountant_report_project/models/accountant_report_mixin.py
odoo/addons/ssi_accountant_report_project/static/description/icon.png
odoo/addons/ssi_accountant_report_project/views/accountant_assurance_report_views.xml
odoo/addons/ssi_accountant_report_project/views/accountant_nonassurance_report_views.xml
odoo14_addon_ssi_accountant_report_project-14.0.1.0.0.dist-info/METADATA
odoo14_addon_ssi_accountant_report_project-14.0.1.0.0.dist-info/WHEEL
odoo14_addon_ssi_accountant_report_project-14.0.1.0.0.dist-info/top_level.txt
odoo14_addon_ssi_accountant_report_project-14.0.1.0.0.dist-info/RECORD
